{
  "version": "5.5.0",
  "flags": {},
  "shapes": [
    {
      "label": "key-nomen",
      "points": [
        [
          121.05263157894706,
          300.0
        ],
        [
          2784.21052631579,
          4021.052631578947
        ]
      ],
      "group_id": null,
      "description": "",
      "shape_type": "rectangle",
      "flags": {},
      "mask": null
    },
    {
      "label": "page-number",
      "points": [
        [
          2631.5789473684217,
          4089.4736842105262
        ],
        [
          2847.3684210526317,
          4178.9473684210525
        ]
      ],
      "group_id": null,
      "description": "",
      "shape_type": "rectangle",
      "flags": {},
      "mask": null
    },
    {
      "label": "key-nomen-date",
      "points": [
        [
          164.91228070175384,
          342.1052631578947
        ],
        [
          775.438596491228,
          524.5614035087718
        ]
      ],
      "group_id": null,
      "description": "",
      "shape_type": "rectangle",
      "flags": {},
      "mask": null
    },
    {
      "label": "key-nomen-title",
      "points": [
        [
          915.0,
          280.0
        ],
        [
          2490.0,
          442.5
        ]
      ],
      "group_id": null,
      "description": "",
      "shape_type": "rectangle",
      "flags": {},
      "mask": null
    },
    {
      "label": "key-nomen-page-number",
      "points": [
        [
          2540.0,
          295.0
        ],
        [
          2687.5,
          400.0
        ]
      ],
      "group_id": null,
      "description": "",
      "shape_type": "rectangle",
      "flags": {},
      "mask": null
    },
    {
      "label": "key-nomen-letters",
      "points": [
        [
          275.0,
          562.5
        ],
        [
          2740.0,
          970.0
        ]
      ],
      "group_id": null,
      "description": "",
      "shape_type": "rectangle",
      "flags": {},
      "mask": null
    },
    {
      "label": "key-nomen-vertical-pairs",
      "points": [
        [
          270.0,
          982.5
        ],
        [
          2395.0,
          1277.5
        ]
      ],
      "group_id": null,
      "description": "",
      "shape_type": "rectangle",
      "flags": {},
      "mask": null
    },
    {
      "label": "key-nomen-nulls",
      "points": [
        [
          260.0,
          1290.0
        ],
        [
          1457.5,
          1487.5
        ]
      ],
      "group_id": null,
      "description": "",
      "shape_type": "rectangle",
      "flags": {},
      "mask": null
    },
    {
      "label": "key-nomen-vertical-pairs",
      "points": [
        [
          282.5,
          1517.5
        ],
        [
          2070.0,
          1737.5
        ]
      ],
      "group_id": null,
      "description": "",
      "shape_type": "rectangle",
      "flags": {},
      "mask": null
    },
    {
      "label": "key-nomen-horizontal-pairs",
      "points": [
        [
          275.0,
          1762.5
        ],
        [
          1277.5,
          3725.0
        ]
      ],
      "group_id": null,
      "description": "",
      "shape_type": "rectangle",
      "flags": {},
      "mask": null
    },
    {
      "label": "key-nomen-horizontal-pairs",
      "points": [
        [
          1530.0,
          1752.5
        ],
        [
          2320.0,
          3185.0
        ]
      ],
      "group_id": null,
      "description": "",
      "shape_type": "rectangle",
      "flags": {},
      "mask": null
    }
  ],
  "imagePath": "img29_right.jpg",
  "imageHeight": 4400,
  "imageWidth": 3400
}